LICENSE
MANIFEST.in
README.md
setup.py
jsonlike/__init__.py
jsonlike/api.py
jsonlike.egg-info/PKG-INFO
jsonlike.egg-info/SOURCES.txt
jsonlike.egg-info/dependency_links.txt
jsonlike.egg-info/requires.txt
jsonlike.egg-info/top_level.txt
tests/__init__.py
tests/jsonlike_test.py
tests/jsonlike_test.py~