Metadata-Version: 1.1
Name: jsonlike
Version: 0.0.2
Summary: repair and parse invalid but jsonlike content
Home-page: https://github.com/shaunvxc/jsonlike
Author: Shaun Viguerie
Author-email: shaunvig114@gmail.com
License: MIT
Platform: UNKNOWN
Classifier: Development Status :: 3 - Alpha
Classifier: Intended Audience :: Developers
Classifier: Intended Audience :: System Administrators
Classifier: Intended Audience :: End Users/Desktop
Classifier: Topic :: System :: Shells
Classifier: Topic :: System :: System Shells
Classifier: License :: OSI Approved :: MIT License
Classifier: Programming Language :: Python :: 2.7
Classifier: Programming Language :: Python :: 3.3
Classifier: Programming Language :: Python :: 3.4
Classifier: Programming Language :: Python :: 3.5
